license_plate_recognition/.ipynb_checkpoints/Test-checkpoint.ipynb
license_plate_recognition/__init__.py
license_plate_recognition/license_plate_recogniser.py
license_plate_recognition/network_swinir.py
license_plate_recognition/super_resolution.py
license_plate_recognition/Test.ipynb
license_plate_recognition/util_calculate_psnr_ssim.py
car_plate_recognition-0.1.3.dist-info/METADATA
car_plate_recognition-0.1.3.dist-info/WHEEL
car_plate_recognition-0.1.3.dist-info/RECORD
