Metadata-Version: 2.3
Name: car-plate-recognition
Version: 0.1.3
Summary: License plate recognition
Author: Your Name
Author-email: you@example.com
Requires-Python: >=3.11
Classifier: Programming Language :: Python :: 3
Classifier: Programming Language :: Python :: 3.11
Classifier: Programming Language :: Python :: 3.12
Classifier: Programming Language :: Python :: 3.13
Requires-Dist: opencv-python (>=4.12.0.88,<5.0.0.0)
Requires-Dist: paddlepaddle (==3.0.0)
Requires-Dist: pytesseract (>=0.3.13,<0.4.0)
Requires-Dist: requests (>=2.32.4,<3.0.0)
Requires-Dist: timm (>=1.0.19,<2.0.0)
